cosmotrek/__init__.py
cosmotrek/logger.py
cosmotrek-0.1.0.dist-info/METADATA
cosmotrek-0.1.0.dist-info/WHEEL
cosmotrek-0.1.0.dist-info/top_level.txt
cosmotrek-0.1.0.dist-info/RECORD
